.gitignore
.travis.yml
CHANGES.rst
LICENSE.txt
MANIFEST.in
README.rst
__init__.py
publish.sh
pyproject.toml
json_cfg_rw.egg-info/PKG-INFO
json_cfg_rw.egg-info/SOURCES.txt
json_cfg_rw.egg-info/dependency_links.txt
json_cfg_rw.egg-info/requires.txt
json_cfg_rw.egg-info/top_level.txt
jsoncfg/__init__.py
jsoncfg/compatibility.py
jsoncfg/compatibility_test.py
jsoncfg/config_classes.py
jsoncfg/config_classes_test.py
jsoncfg/exceptions.py
jsoncfg/functions.py
jsoncfg/functions_test.py
jsoncfg/library_usage_test.py
jsoncfg/parser.py
jsoncfg/parser_listener.py
jsoncfg/parser_test.py
jsoncfg/text_encoding.py
jsoncfg/text_encoding_test.py
jsoncfg/tree_config.py
jsoncfg/tree_python.py
jsoncfg/utils.py
jsoncfg/value_mappers.py
jsoncfg/value_mappers_test.py
jsoncfg/version.py